natas/__init__.py
natas/download.py
natas/get_wiktionary_lemmas.py
natas/normalize.py
natas/ocr_builder.py
natas/wiktionary_lemmas.json
natas/models/README.txt
natas-1.2.1.dist-info/LICENSE
natas-1.2.1.dist-info/METADATA
natas-1.2.1.dist-info/WHEEL
natas-1.2.1.dist-info/top_level.txt
natas-1.2.1.dist-info/RECORD
