Metadata-Version: 2.1
Name: natas
Version: 1.2.1
Summary: Python library for processing historical English
Home-page: https://github.com/mikahama/natas
Author: Mika Hämäläinen
Author-email: mika@flyforpoints.com
License: Apache 2.0
Project-URL: Bug Reports, https://github.com/mikahama/natas/issues
Project-URL: Developer, https://mikakalevi.com/
Keywords: historical English,spelling normalization,OCR error correction
Classifier: Development Status :: 5 - Production/Stable
Classifier: Intended Audience :: Developers
Classifier: Topic :: Text Processing :: Linguistic
Classifier: Programming Language :: Python :: 3
License-File: LICENSE
Requires-Dist: configargparse
Requires-Dist: distance
Requires-Dist: spacy >=2.1.4
Requires-Dist: mikatools >=0.0.6
Requires-Dist: OpenNMT-py ==2.1.2
